meuw_bids_pftools/__init__.py
meuw_bids_pftools/tools/__init__.py
meuw_bids_pftools/tools/context_blob_url_generator.py
meuw_bids_pftools/tools/utils.py
meuw_bids_pftools/yamls/context_blob_url_generator.yaml
tests/__init__.py
tests/test_custom_search.py
tests/test_dynamic_list_tool.py
meuw_bids_pftools-0.0.2.dist-info/METADATA
meuw_bids_pftools-0.0.2.dist-info/WHEEL
meuw_bids_pftools-0.0.2.dist-info/entry_points.txt
meuw_bids_pftools-0.0.2.dist-info/top_level.txt
meuw_bids_pftools-0.0.2.dist-info/RECORD
