Metadata-Version: 2.1
Name: meuw_bids_pftools
Version: 0.0.2
Summary: This is my tools package
